LICENSE
README.md
setup.py
tunetools/__init__.py
tunetools/config.py
tunetools/core.py
tunetools/db_utils.py
tunetools/decorator.py
tunetools/main.py
tunetools/package_info.py
tunetools/search_space.py
tunetools/search_types.py
tunetools/session_logger.py
tunetools/statistics.py
tunetools.egg-info/PKG-INFO
tunetools.egg-info/SOURCES.txt
tunetools.egg-info/dependency_links.txt
tunetools.egg-info/entry_points.txt
tunetools.egg-info/requires.txt
tunetools.egg-info/top_level.txt