Metadata-Version: 2.1
Name: tunetools
Version: 1.1.1
Summary: A powerful tuning and result management toolkit for AI experiments
Home-page: https://github.com/Keytoyze/TuneTools
Author: Keytoize
Author-email: cmx_1007@foxmail.com
License: UNKNOWN
Platform: UNKNOWN
License-File: LICENSE
